skeleton.py
skeleton_mindcloud-0.3.0.dist-info/LICENSE
skeleton_mindcloud-0.3.0.dist-info/WHEEL
skeleton_mindcloud-0.3.0.dist-info/METADATA
skeleton_mindcloud-0.3.0.dist-info/RECORD
